djangocms_socialshare/__init__.py
djangocms_socialshare/cms_plugins.py
djangocms_socialshare/models.py
djangocms_socialshare/migrations/0001_initial.py
djangocms_socialshare/migrations/0002_set_button_empty_by_default.py
djangocms_socialshare/migrations/0003_add_social_links_plugin.py
djangocms_socialshare/migrations/0004_add_background_color.py
djangocms_socialshare/migrations/__init__.py
djangocms_socialshare/static/djangocms_socialshare/djangocms-socialshare.css
djangocms_socialshare/templates/djangocms_socialshare/socialshare-plugin.html
djangocms_socialshare/templatetags/__init__.py
djangocms_socialshare/templatetags/socialshare.py
djangocms_socialshare-1.0.0.5.dist-info/METADATA
djangocms_socialshare-1.0.0.5.dist-info/WHEEL
djangocms_socialshare-1.0.0.5.dist-info/top_level.txt
djangocms_socialshare-1.0.0.5.dist-info/RECORD
