Metadata-Version: 2.1
Name: djangocms-socialshare
Version: 1.0.0.5
Summary: UNKNOWN
Home-page: https://gitlab.com/what-digital/djangocms-socialshare
Author: Victor Yunenko
Author-email: victor.yunenko+pypi@pm.me
License: MIT
Keywords: django
Platform: UNKNOWN
Classifier: Development Status :: 4 - Beta
Classifier: Framework :: Django :: 2.2
Classifier: Framework :: Django CMS :: 3.7
Classifier: Programming Language :: Python :: 3.6
Requires-Dist: django (<4,>=2.2)
Requires-Dist: django-cms (<4,>=3.7.2)
